legal_documents_cn/__init__.py
legal_documents_cn/apitest.py
legal_documents_cn/criminal_law.csv
legal_documents_cn/criminal_law_cn.py
legal_documents_cn/process_data.py
legal_documents_cn/run_start_api.py
legal_documents_cn/start_api.py
legal_documents_cn-0.0.12.dist-info/LICENSE
legal_documents_cn-0.0.12.dist-info/METADATA
legal_documents_cn-0.0.12.dist-info/WHEEL
legal_documents_cn-0.0.12.dist-info/top_level.txt
legal_documents_cn-0.0.12.dist-info/RECORD
