Metadata-Version: 2.1
Name: legal-documents-cn
Version: 0.0.12
Summary: Chinese legal documents, you can get certain legal term content by the code of term and the code of term by its content
Home-page: https://github.com/1558359609/criminal_law_api
Author: dongyuwu omnilab
Author-email: 1558359609@qq.com
Classifier: Programming Language :: Python :: 3
Classifier: License :: OSI Approved :: MIT License
Classifier: Operating System :: OS Independent
Requires-Python: >=3.7
License-File: LICENSE
Requires-Dist: pandas (>=1.5.0)
Requires-Dist: nltk (>=3.7)
